tencent_cos_python/__init__.py
tencent_cos_python/cos_client_factory.py
tencent_cos_python/cos_object.py
tencent_cos_python/logger.py
tencent_cos_python/util.py
tencent_cos_python_azleal-0.0.9.dist-info/LICENSE
tencent_cos_python_azleal-0.0.9.dist-info/METADATA
tencent_cos_python_azleal-0.0.9.dist-info/WHEEL
tencent_cos_python_azleal-0.0.9.dist-info/top_level.txt
tencent_cos_python_azleal-0.0.9.dist-info/RECORD
