Metadata-Version: 2.1
Name: tencent-cos-python-azleal
Version: 0.0.9
Summary: easy use for tencent_cos_python client
Home-page: https://github.com/Azleal/tencent-cos-python
Author: Azleal
Author-email: azleal.mr@gmail.com
License: UNKNOWN
Platform: UNKNOWN
Classifier: Programming Language :: Python :: 3
Classifier: License :: OSI Approved :: MIT License
Classifier: Operating System :: OS Independent
License-File: LICENSE
Requires-Dist: cos-python-sdk-v5
